sopel_doubts/__init__.py
sopel_doubts/plugin.py
sopel_doubts-1.0.1.dist-info/licenses/LICENSE
sopel_doubts-1.0.1.dist-info/METADATA
sopel_doubts-1.0.1.dist-info/WHEEL
sopel_doubts-1.0.1.dist-info/entry_points.txt
sopel_doubts-1.0.1.dist-info/top_level.txt
sopel_doubts-1.0.1.dist-info/RECORD
