Metadata-Version: 2.4
Name: sopel-doubts
Version: 1.0.1
Summary: Press X to doubt.
Author-email: xnaas <me@xnaas.info>
Maintainer-email: dgw <dgw@technobabbl.es>
License-Expression: Unlicense
Project-URL: Homepage, https://github.com/dgw/sopel-doubts
Project-URL: Bug Tracker, https://github.com/dgw/sopel-doubts/issues
Platform: Linux x86, x86-64
Classifier: Development Status :: 5 - Production/Stable
Classifier: Operating System :: POSIX :: Linux
Classifier: Programming Language :: Python :: 3.8
Classifier: Programming Language :: Python :: 3.9
Classifier: Programming Language :: Python :: 3.10
Classifier: Programming Language :: Python :: 3.11
Classifier: Programming Language :: Python :: 3.12
Classifier: Programming Language :: Python :: 3 :: Only
Classifier: Topic :: Communications :: Chat :: Internet Relay Chat
Requires-Python: <4,>=3.8
License-File: LICENSE
Requires-Dist: sopel>=7.1
Dynamic: license-file
